marketsight/__init__.py
marketsight/__version__.py
marketsight/_compat.py
marketsight/application_api.py
marketsight/exceptions.py
marketsight/http_client.py
marketsight-0.1.2.dist-info/LICENSE
marketsight-0.1.2.dist-info/METADATA
marketsight-0.1.2.dist-info/WHEEL
marketsight-0.1.2.dist-info/top_level.txt
marketsight-0.1.2.dist-info/RECORD
