Metadata-Version: 2.1
Name: marketsight
Version: 0.1.2
Summary: Python bindings for the MarketSight API
Home-page: https://marketsight.readthedocs.io/en/latest
Author: MarketSight, LLC
Author-email: support@marketsight.com
License: MIT
Project-URL: Documentation, https://marketsight.readthedocs.io/en/latest
Project-URL: Say Thanks!, https://saythanks.io/to/marketsight
Project-URL: Bug Reports, https://github.com/dynata/msight-csl/issues
Project-URL: Source, https://github.com/dynata/msight-csl/
Keywords: marketsight cross-tab xtab statistical analysis analytics
Platform: UNKNOWN
Classifier: Development Status :: 1 - Planning
Classifier: Environment :: Web Environment
Classifier: Operating System :: OS Independent
Classifier: Intended Audience :: Developers
Classifier: Topic :: Software Development :: Libraries
Classifier: Topic :: Utilities
Classifier: Topic :: Internet :: WWW/HTTP :: Dynamic Content
Classifier: Topic :: Software Development :: Libraries :: Python Modules
Classifier: License :: OSI Approved :: MIT License
Classifier: Programming Language :: Python :: 3
Classifier: Programming Language :: Python :: 3.4
Classifier: Programming Language :: Python :: 3.5
Classifier: Programming Language :: Python :: 3.6
Classifier: Programming Language :: Python :: 3.7
Requires-Python: >=3.0, !=3.0.*, !=3.1.*, !=3.2.*, !=3.3.*, <4
License-File: LICENSE
Requires-Dist: validator-collection (>=1.5.0)
Requires-Dist: simplejson (>=3.0)
Requires-Dist: bravado (>=10.6.0)
Requires-Dist: dpath (>=2.0.1)
Requires-Dist: chardet (>=4.0.0)
Requires-Dist: jsonschema (<4.0,>=3.0)
Provides-Extra: dev
Requires-Dist: check-manifest ; extra == 'dev'
Requires-Dist: sphinx ; extra == 'dev'
Requires-Dist: sphinx-rtd-theme ; extra == 'dev'
Requires-Dist: sphinx-tabs ; extra == 'dev'
Requires-Dist: readme-renderer ; extra == 'dev'
Requires-Dist: restview ; extra == 'dev'
Requires-Dist: python-dotenv ; extra == 'dev'
Provides-Extra: test
Requires-Dist: coverage ; extra == 'test'
Requires-Dist: pytest ; extra == 'test'
Requires-Dist: pytest-benchmark ; extra == 'test'
Requires-Dist: pytest-cov ; extra == 'test'
Requires-Dist: tox ; extra == 'test'
Requires-Dist: codecov ; extra == 'test'
Requires-Dist: python-dotenv ; extra == 'test'
